{
  "name": [
    {
      "name": "著作權法",
      "start_date": "1928-05-14"
    }
  ],
  "history": [
    {
      "passed_date": "1928-05-14",
      "enactment_date": "1928-05-14"
    },
    {
      "passed_date": "1944-03-31",
      "enactment_date": "1944-04-27"
    },
    {
      "passed_date": "1948-12-31",
      "enactment_date": "1949-01-13"
    },
    {
      "passed_date": "1964-06-30",
      "enactment_date": "1964-07-10"
    },
    {
      "passed_date": "1985-06-28",
      "enactment_date": "1985-07-10"
    },
    {
      "passed_date": "1990-01-11",
      "enactment_date": "1990-01-24"
    },
    {
      "passed_date": "1992-05-22",
      "enactment_date": "1992-06-10"
    },
    {
      "passed_date": "1992-06-19",
      "enactment_date": "1992-07-06"
    },
    {
      "passed_date": "1993-04-22",
      "enactment_date": "1993-04-24"
    },
    {
      "passed_date": "1997-12-30",
      "enactment_date": "1998-01-21"
    },
    {
      "passed_date": "2001-10-25",
      "enactment_date": "2001-11-12"
    },
    {
      "passed_date": "2003-06-06",
      "enactment_date": "2003-07-09"
    },
    {
      "passed_date": "2004-08-24",
      "enactment_date": "2004-09-01"
    },
    {
      "passed_date": "2006-05-05",
      "enactment_date": "2006-05-30",
      "enforcement_date": "2006-07-01"
    },
    {
      "passed_date": "2007-06-14",
      "enactment_date": "2007-07-11"
    },
    {
      "passed_date": "2009-04-21",
      "enactment_date": "2009-05-13"
    },
    {
      "passed_date": "2010-01-05",
      "enactment_date": "2010-02-10"
    },
    {
      "passed_date": "2010-01-12",
      "enactment_date": "2010-02-10"
    }
  ],
  "lyID": "01176",
  "PCode": "J0070017"
}