{
  "name": [
    {
      "name": "商港法",
      "start_date": "1980-04-15"
    }
  ],
  "history": {
    "1980-04-15": "制定51條",
    "1980-05-02": "公布",
    "1986-11-18": "修正第2, 4, 12, 15, 16, 18, 20, 46至48條\n增訂第16之1, 23之1, 50之1條",
    "1986-11-28": "公布",
    "1987-07-15": "修正第7條",
    "1987-08-07": "公布",
    "1995-12-21": "修正第12條",
    "1996-01-10": "公布",
    "1997-04-15": "修正第7, 51條",
    "1997-05-07": "公布",
    "2001-10-30": "增訂第16之2, 23之2, 35之1, 43之1, 47之1條\n刪除第7, 34, 35條\n修正第15, 16之1, 17, 33, 36, 44, 46至48, 50, 51條\n第7條及第15條自民國91年1月1日施行",
    "2001-11-21": "公布",
    "2002-12-13": "修正第3, 4, 6, 11, 49條",
    "2003-01-02": "公布",
    "2005-01-14": "修正第18條",
    "2005-02-05": "公布",
    "2011-12-06": "修正全文76條",
    "2011-12-28": "公布",
    "2012-03-01": "施行"
  },
  "lyID": "02028",
  "PCode": "K0080001"
}