{
  "name": [
    {
      "name": "國營事業管理法",
      "start_date": "1948-12-31"
    }
  ],
  "history": {
    "1948-12-31": "制定38條",
    "1949-01-20": "公布",
    "1997-12-19": "修正第38條\n刪除第23條",
    "1998-01-07": "公布",
    "1999-05-27": "施行",
    "2000-06-30": "修正第35條",
    "2000-07-19": "公布",
    "2001-05-01": "施行",
    "2002-05-24": "修正第35條",
    "2002-06-19": "公布",
    "2003-01-01": "施行",
    "2007-12-21": "修正第3條",
    "2008-01-09": "公布",
    "2008-02-01": "施行",
    "2011-12-14": "修正第15, 31, 33, 37條",
    "2011-12-28": "公布",
    "2012-01-20": "施行"
  },
  "lyID": "01934",
  "PCode": "J0120001"
}