[
  {
    "article": "1",
    "lyID": "01534",
    "content": "中國農民銀行經國民政府之特許為供給農民資金，復興農村經濟，促進農業生產之改良進步，依照股份有限公司之組織設立之。\n",
    "passed_date": "1935-05-14"
  },
  {
    "article": "2",
    "lyID": "01534",
    "content": "中國農民銀行資本總額定為國幣一千萬元，分為十萬股，每股國幣一百元，一次繳足。除由財政部認二萬五千股及各省市政府分別認股外，餘由人民承購。\n各省市政府所認股額，均不得少於二千五百股。\n第一項資本總額收足後，如因業務上之必要，須增加股本時，得由股東會議決，呈請財政部核准增加之。\n",
    "passed_date": "1935-05-14"
  },
  {
    "article": "3",
    "lyID": "01534",
    "content": "中國農民銀行設總行於溝口並於其他必要區域酌設分支行及辦事處，或與其他銀行號暨農業金融機關訂立代理契約。但分支行及辦事處之設立，須呈請財政部核准備案。\n",
    "passed_date": "1935-05-14"
  },
  {
    "article": "4",
    "lyID": "01534",
    "content": "中國農民銀行股票概用記名式，股東以有中華民國國籍者為限。\n",
    "passed_date": "1935-05-14"
  },
  {
    "article": "5",
    "lyID": "01534",
    "content": "中國農民銀行營業年限為三十年，自本條例公布日起算。期滿時得由股東會議決，呈請財政部核准延長之。\n",
    "passed_date": "1935-05-14"
  },
  {
    "article": "6",
    "lyID": "01534",
    "content": "中國農民銀行之營業範圍如左。\n一、放款於農民組織之合作社及合作社聯合社。\n二、放款於農業之發展事業。\n三、放款於水利備荒事業。\n四、經營農業倉庫，及放款於農產、農具之改良事業。\n五、動產、不動產之抵押放款及保證信用放款。\n六、票據之承受或貼現。\n七、收受各項存款及儲蓄存款。\n八、代理收解各種款項。\n九、辦理匯兌及同業短期往來。\n十、買賣有價證券。\n十一、其他農民銀行應有之業務。\n",
    "passed_date": "1935-05-14"
  },
  {
    "article": "7",
    "lyID": "01534",
    "content": "中國農民銀行農業放款，以供左列各項用途為限。\n一、購買耕牛、籽種、肥料、畜種及各種農業原料。\n二、購辦或修理農業應用器械。\n三、農業品之保管、運輸及製造。\n四、修造農業應用房屋及場所。\n五、其他與農民經濟或農業改良有密切關係之事項。\n",
    "passed_date": "1935-05-14"
  },
  {
    "article": "8",
    "lyID": "01534",
    "content": "中國農民銀行之放款期限，最長不得過五年。\n",
    "passed_date": "1935-05-14"
  },
  {
    "article": "9",
    "lyID": "01534",
    "content": "中國農民銀行不動產抵押放款之總額，不得超過實收資本及公積金之總數。\n",
    "passed_date": "1935-05-14"
  },
  {
    "article": "10",
    "lyID": "01534",
    "content": "中國農民銀行農業放款，不得少於放款總額百分之六十。並於每屆年終結算時，於資產負債表上以適當之科目表現之。\n",
    "passed_date": "1935-05-14"
  },
  {
    "article": "11",
    "lyID": "01534",
    "content": "中國農民銀行得發行兌換券。其發行條例另定之。\n",
    "passed_date": "1935-05-14"
  },
  {
    "article": "12",
    "lyID": "01534",
    "content": "中國農民銀行經國民政府之特准，得發行農業債券。但發行總額，不得超過已收資本之五倍，並不得超過放款之總數，其每年償還額，不得少於收回放款百分之六十以上。\n",
    "passed_date": "1935-05-14"
  },
  {
    "article": "13",
    "lyID": "01534",
    "content": "中國農民銀行不得經營左列各款事項。\n一、收買本銀行股票，並以本銀行股票為擔保之放款。\n二、買賣不動產。但業務上必要之不動產，不在此限。\n三、以投機之目的而從事於有價證券之買賣。\n",
    "passed_date": "1935-05-14"
  },
  {
    "article": "14",
    "lyID": "01534",
    "content": "中國農民銀行設董事十五人，組織董事會，由股東會在百股以上之股東中選任之，任期三年，每年改選三分之一，連選得連任。但第一屆董事之任期，於首次開董事會時以抽籤決定之。\n",
    "passed_date": "1935-05-14"
  },
  {
    "article": "15",
    "lyID": "01534",
    "content": "中國農民銀行設常務董事七人，由董事互選之，並由常務董事互選一人為董事長，均以董事之任期為任期。\n",
    "passed_date": "1935-05-14"
  },
  {
    "article": "16",
    "lyID": "01534",
    "content": "中國農民銀行設監察人五人，由股東會在百股以上之股東中選任之，任期一年，連選得連任。\n",
    "passed_date": "1935-05-14"
  },
  {
    "article": "17",
    "lyID": "01534",
    "content": "中國農民銀行設總經理一人，協理一人，由董事長提經董事會同意遴聘，呈請財政部核准備案。\n總經理因事故不能執行職務時，由協理代理之。\n",
    "passed_date": "1935-05-14"
  },
  {
    "article": "18",
    "lyID": "01534",
    "content": "中國農民銀行之股東會，分為左列二種。\n一、股東常會。\n二、股東臨時會。\n",
    "passed_date": "1935-05-14"
  },
  {
    "article": "19",
    "lyID": "01534",
    "content": "股東常會每年於總行所在地開會一次，由董事會召集之。\n",
    "passed_date": "1935-05-14"
  },
  {
    "article": "20",
    "lyID": "01534",
    "content": "董事會認為有重要事件必須開會時，得召集股東臨時會。\n",
    "passed_date": "1935-05-14"
  },
  {
    "article": "21",
    "lyID": "01534",
    "content": "董事會遇有董事過半數，或監察人，或有股份總數二十分一以上之股東，因重要事件請求會議時，得召集股東臨時會。\n",
    "passed_date": "1935-05-14"
  },
  {
    "article": "22",
    "lyID": "01534",
    "content": "股東會開會時，股東須於會期六十日以前登記者，始得出席會議。\n",
    "passed_date": "1935-05-14"
  },
  {
    "article": "23",
    "lyID": "01534",
    "content": "股東會股東因事故不能到會時，其委託代理人，以股東為限。\n",
    "passed_date": "1935-05-14"
  },
  {
    "article": "24",
    "lyID": "01534",
    "content": "中國農民銀行每年營業所得純利，提百分之二十為公積金，百分之四十五為股利，餘為特別公積金及職員獎勵金。\n職員獎勵金，不得超過其全年薪俸四分之一。\n前二項純利之分配，須經股東會通過，呈報財政部備案。\n",
    "passed_date": "1935-05-14"
  },
  {
    "article": "25",
    "lyID": "01534",
    "content": "前條公積金得用以填補資本之損失及維持股利之平均。\n",
    "passed_date": "1935-05-14"
  },
  {
    "article": "26",
    "lyID": "01534",
    "content": "中國農民銀行依照本條例詳訂章程，經股東會議決，呈請財政部、實業部備案。\n",
    "passed_date": "1935-05-14"
  },
  {
    "article": "27",
    "lyID": "01534",
    "content": "本條例自公布日施行。\n",
    "passed_date": "1935-05-14"
  },
  {
    "article": "3",
    "lyID": "01534",
    "content": "中國農民銀行總行設於首都，並得於其他必要區域設分支行及辦事處，或與其他銀行總號及農業金融機關訂立代理契約。但分支行及辦事處之設立，應經財政部核准。\n",
    "passed_date": "1937-05-28"
  },
  {
    "article": "1",
    "lyID": "01534",
    "content": "中國農民銀行，經國民政府之特許，為供給農民資金，復興農村經濟，促進農業生產之改良進步，依照股份有限公司之組織設立之。\n",
    "passed_date": "1941-08-09"
  },
  {
    "article": "2",
    "lyID": "01534",
    "content": "中國農民銀行資本總額，定為國幣二千萬元，分為二十萬股，每股國幣一百元，一次繳足，除由財政部認十二萬五千股及各省市政府分別認股外，餘由人民承購。\n前項資本總額收足後，如因業務上之必要，須增加股本時，得由股東會議決，呈請財政部核准增加之。\n",
    "passed_date": "1941-08-09"
  },
  {
    "article": "3",
    "lyID": "01534",
    "content": "中國農民銀行設總管理處，並得酌設分支行及辦事處，或與其他銀行號暨農業金融機關訂立代理契約。但分支行及辦事處之設立，須呈請財政部核准備案。\n",
    "passed_date": "1941-08-09"
  },
  {
    "article": "4",
    "lyID": "01534",
    "content": "中國農民銀行股票，概用記名式，股東以有中華民國國籍者為限。\n",
    "passed_date": "1941-08-09"
  },
  {
    "article": "5",
    "lyID": "01534",
    "content": "中國農民銀行營業年限為三十年，自本條例公布日起算，期滿時，得由股東會議決，呈請財政部核准延長之。\n",
    "passed_date": "1941-08-09"
  },
  {
    "article": "6",
    "lyID": "01534",
    "content": "中國農民銀行之營業範圍如左：\n一、放款於農民組織之合作社及合作社聯合社。\n二、放款於農業之發展事業。\n三、放款於水利備荒事業。\n四、經營農業倉庫及放款於農業農具之改良事業。\n五、動產不動產之抵押放款及保證信用放款。\n六、票據之承受或貼現。\n七、收受各項存款及儲蓄存款。\n八、代理收解各種款項。\n九、辦理匯兌及同業短期往來。\n十、買賣有價證券。\n十一、辦理信託事業。\n十二、其他農民銀行應有之業務。\n",
    "passed_date": "1941-08-09"
  },
  {
    "article": "7",
    "lyID": "01534",
    "content": "中國農民銀行農業放款，以供左列各項用途為限：\n一、購買耕牛、種籽、肥料、畜種及各種農業原料。\n二、購辦或修理農業應用器械。\n三、農業品之保管、運輸及製造。\n四、修造農業應用房屋及場所。\n五、其他與農民經濟或農業改良有密切關係之事項。\n",
    "passed_date": "1941-08-09"
  },
  {
    "article": "10",
    "lyID": "01534",
    "content": "中國農民銀行農業放款，不得少於放款總額百分之六十，並於每屆年終結算時，於資產負債表上，以適當之科目表現之。\n",
    "passed_date": "1941-08-09"
  },
  {
    "article": "11",
    "lyID": "01534",
    "content": "中國農民銀行於總管理處設土地金融處，兼辦土地金融業務；其兼辦土地金融業務，另以法律定之。\n",
    "passed_date": "1941-08-09"
  },
  {
    "article": "12",
    "lyID": "01534",
    "content": "中國農民銀行得依法發行兌換券。\n",
    "passed_date": "1941-08-09"
  },
  {
    "article": "13",
    "lyID": "01534",
    "content": "中國農民銀行經國民政府之特准，得發行農業債券。但發行總額不得超過已收資本之五倍，並不得超過放款之總數，其每年償還額不得少於收回放款百分之六十以上。\n",
    "passed_date": "1941-08-09"
  },
  {
    "article": "14",
    "lyID": "01534",
    "content": "中國農民銀行不得經營左列各款事項：\n一、收買本銀行股票，並於本銀行股票為擔保之放款。\n二、買賣不動產。但業務上必要之不動產，不在此限。\n三、以投機之目的而從事於有價證券之買賣。\n",
    "passed_date": "1941-08-09"
  },
  {
    "article": "15",
    "lyID": "01534",
    "content": "中國農民銀行設董事十五人，組織董事會，由股東會在百股以上之股東中選任之，任期三年，每年改選三分之一，連選得連任。但第一屆董事之任期，於首次開董事會時，以抽籤決定之。\n",
    "passed_date": "1941-08-09"
  },
  {
    "article": "16",
    "lyID": "01534",
    "content": "中國農民銀行設常務董事七人，由董事互選之，並由常務董事中互選一人為董事長，均以董事之任期為任期。\n",
    "passed_date": "1941-08-09"
  },
  {
    "article": "17",
    "lyID": "01534",
    "content": "中國農民銀行設監察人五人，由股東會在百股以上之股東中選任之，任期一年，連選得任連。\n",
    "passed_date": "1941-08-09"
  },
  {
    "article": "18",
    "lyID": "01534",
    "content": "中國農民銀行設總經理一人，協理一人至三人，由董事長提經董事會同意遴聘，呈請財政部核准備案。\n總經理因事故不能執行職務時，由協理代理之。\n",
    "passed_date": "1941-08-09"
  },
  {
    "article": "19",
    "lyID": "01534",
    "content": "中國農民銀行之股東會，分為左列二種。\n一、股東常會。\n二、股東臨時會。\n",
    "passed_date": "1941-08-09"
  },
  {
    "article": "20",
    "lyID": "01534",
    "content": "股東常會每年於總管理處所在地開會一次，由董事會召集之。\n",
    "passed_date": "1941-08-09"
  },
  {
    "article": "21",
    "lyID": "01534",
    "content": "董事會認為有重要事件必須開會時，得召集股東臨時會。\n",
    "passed_date": "1941-08-09"
  },
  {
    "article": "22",
    "lyID": "01534",
    "content": "董事會遇有董事過半數或監察人或有股份總數二十分之一以上之股東，因重要事件請求會議時，得召集股東臨時會。\n",
    "passed_date": "1941-08-09"
  },
  {
    "article": "23",
    "lyID": "01534",
    "content": "股東會開會時，股東須於會期六十日以前登記者，始得出席會議。\n",
    "passed_date": "1941-08-09"
  },
  {
    "article": "24",
    "lyID": "01534",
    "content": "股東會股東因事故不能到會時，其委託代理人以股東為限。\n",
    "passed_date": "1941-08-09"
  },
  {
    "article": "25",
    "lyID": "01534",
    "content": "中國農民銀行每年營業所得純利，提百分之二十為公積金，百分之四十五為股利，餘為特別公積金及職員獎勵金。\n職員獎勵金不得超過其全年薪俸四分之一。\n前二項純利之分配，須經股東會通過，呈報財政部備案。\n",
    "passed_date": "1941-08-09"
  },
  {
    "article": "26",
    "lyID": "01534",
    "content": "前條公積金，得用以填補資本之損失及維持股利之平均。\n",
    "passed_date": "1941-08-09"
  },
  {
    "article": "27",
    "lyID": "01534",
    "content": "中國農民銀行應依照本條例，詳訂章程，經股東會議決，呈報財政部、農林部核准。\n",
    "passed_date": "1941-08-09"
  },
  {
    "article": "28",
    "lyID": "01534",
    "content": "本條例自公布日施行。\n",
    "passed_date": "1941-08-09"
  },
  {
    "article": "1",
    "lyID": "01534",
    "content": "中國農民銀行（以下簡稱本行）經中央政府特許，為供給農業信用，發展農村經濟，促進農業產銷之農業專業銀行。並依股份有限公司之組織設立之。\n",
    "passed_date": "1980-12-02"
  },
  {
    "article": "2",
    "lyID": "01534",
    "content": "本行資本總額定為新臺幣伍拾億元。\n前項資本總額如有增減之必要時，得由董事會議決，報經財政部核轉行政院核定之。\n",
    "passed_date": "1980-12-02"
  },
  {
    "article": "3",
    "lyID": "01534",
    "content": "本行股東，以中華民國國民或法人為限。\n",
    "passed_date": "1980-12-02"
  },
  {
    "article": "4",
    "lyID": "01534",
    "content": "本行總管理處設於中華民國中央政府所在地，並得設立分支機構。\n",
    "passed_date": "1980-12-02"
  },
  {
    "article": "5",
    "lyID": "01534",
    "content": "本行經營左列業務：\n一、收受各種存款。\n二、辦理農業性放款及保證。\n三、辦理國內外匯兌及貨物押匯。\n四、投資農業生產運銷事業。\n五、辦理農業性證券之認購、承銷及保證。\n六、輔導協助其所授信或投資之事業改進生產技術與經營管理。\n七、其他經財政部核定或中央銀行特許辦理之業務。\n",
    "passed_date": "1980-12-02"
  },
  {
    "article": "6",
    "lyID": "01534",
    "content": "本行對農業生產運銷事業之投資，除經財政部核准者外，總額不得超過本行淨值百分之三十；其對每一企業之投資金額，不得超過本行淨值百分之五及該企業資本總額百分之二十五。\n前項投資，應經本行董事會通過後始得辦理。\n",
    "passed_date": "1980-12-02"
  },
  {
    "article": "7",
    "lyID": "01534",
    "content": "本行為加強農業信用調節功能，得收受發展農業有關之各項基金存款，並透過農會與農業信用組織吸收農村資金，以供應農業信用與辦理有關農民家計金融業務。\n",
    "passed_date": "1980-12-02"
  },
  {
    "article": "8",
    "lyID": "01534",
    "content": "本行對農業放款，不得少於放款總額百分之六十。\n",
    "passed_date": "1980-12-02"
  },
  {
    "article": "9",
    "lyID": "01534",
    "content": "本行為籌措資金，經財政部核准，得在國內外發行金融債券。\n",
    "passed_date": "1980-12-02"
  },
  {
    "article": "10",
    "lyID": "01534",
    "content": "本行置董事十五人，組織董事會。公股及民股董事名額照股權比例分配之。公股董事由財政部指定，民股董事由股東會就民股股東中選任之；任期均三年，連選得連任。\n",
    "passed_date": "1980-12-02"
  },
  {
    "article": "11",
    "lyID": "01534",
    "content": "本行置常務董事七人，由董事互選之，並由常務董事互選一人為董事長，任期與董事同。\n",
    "passed_date": "1980-12-02"
  },
  {
    "article": "12",
    "lyID": "01534",
    "content": "董事會之職權如左：\n一、業務方針及計畫之核定事項。\n二、分支機構之設立、撤銷或變更審議事項。\n三、預算、決算之審議事項。\n四、放款與保證業務授權額度之審定及超過授權額度案件之核定事項。\n五、高級職員任免之審定事項。\n六、重要章則及契約之審定事項。\n七、本條例及本行章程規定之其他事項。\n前項各款職權，董事會得以一部或全部授權常務董事會；常務董事會之決議，應彙報董事會核備。\n",
    "passed_date": "1980-12-02"
  },
  {
    "article": "13",
    "lyID": "01534",
    "content": "本行置監察人五人，組織監察人會。公股及民股監察人名額，照股權比例分配之。公股監察人由財政部指定，民股監察人由股東會就民股股東中選任之；任期均三年，連選得連任。\n本行置常駐監察人一人，由監察人互選之，任期與監察人同。\n",
    "passed_date": "1980-12-02"
  },
  {
    "article": "14",
    "lyID": "01534",
    "content": "監察人會之職權如左：\n一、各項帳目之查核及資產負債之定期檢查事項。\n二、年終決算之審核事項。\n三、違背本條例及本行章則之檢舉事項。\n四、依照法令及本行章程規定之其他事項。\n前項各款職權，監察人會得以一部或全部授權常駐監察人；常駐監察人所作之處理事項，應彙報於監察人會。\n",
    "passed_date": "1980-12-02"
  },
  {
    "article": "15",
    "lyID": "01534",
    "content": "本行置總經理一人，副總經理一人至三人，由董事長提經董事會同意，並報請財政部核准後聘任之。\n",
    "passed_date": "1980-12-02"
  },
  {
    "article": "16",
    "lyID": "01534",
    "content": "本行每年營業所得純利，應先提取百分之四十為法定盈餘公積。\n",
    "passed_date": "1980-12-02"
  },
  {
    "article": "17",
    "lyID": "01534",
    "content": "本行經營業務所發生呆帳之核銷，由財政部依所得稅法，核定額度，授權董事會辦理。\n",
    "passed_date": "1980-12-02"
  },
  {
    "article": "18",
    "lyID": "01534",
    "content": "本條例未規定事項，依銀行法、公司法及其他有關法律規定辦理。\n",
    "passed_date": "1980-12-02"
  },
  {
    "article": "19",
    "lyID": "01534",
    "content": "本條例自公布日施行。\n",
    "passed_date": "1980-12-02"
  },
  {
    "article": "2",
    "lyID": "01534",
    "content": "（刪除）\n",
    "passed_date": "2000-01-15"
  },
  {
    "article": "3",
    "lyID": "01534",
    "content": "（刪除）\n",
    "passed_date": "2000-01-15"
  },
  {
    "article": "8",
    "lyID": "01534",
    "content": "本行對農業放款，不得少於放款總額之一定比率。\n前項比率，由中央主管機關定之。\n",
    "passed_date": "2000-01-15"
  },
  {
    "article": "10",
    "lyID": "01534",
    "content": "本行置董事十五人，組織董事會，董事由股東會就股東中選任之。董事任期三年，得連選連任。\n本行置常務董事七人，由董事互選之，並由常務董事互選一人為董事長，任期與董事同。\n",
    "passed_date": "2000-01-15"
  },
  {
    "article": "11",
    "lyID": "01534",
    "content": "（刪除）\n",
    "passed_date": "2000-01-15"
  },
  {
    "article": "13",
    "lyID": "01534",
    "content": "本行置監察人五人，組織監察人會，監察人由股東會就股東中選任之。監察人任期三年，得連選連任。\n本行置常駐監察人一人，由監察人互選之，任期與監察人同。\n",
    "passed_date": "2000-01-15"
  },
  {
    "article": "16",
    "lyID": "01534",
    "content": "（刪除）\n",
    "passed_date": "2000-01-15"
  },
  {
    "article": "17",
    "lyID": "01534",
    "content": "（刪除）\n",
    "passed_date": "2000-01-15"
  }
]