[
  {
    "article": "1",
    "lyID": "01019",
    "content": "經濟部管理全國經濟行政及經濟建設事務。\n",
    "passed_date": "1949-04-19"
  },
  {
    "article": "2",
    "lyID": "01019",
    "content": "經濟部對於各地方最高級行政長官執行本部主管事務，有指示監督之責。\n",
    "passed_date": "1949-04-19"
  },
  {
    "article": "3",
    "lyID": "01019",
    "content": "經濟部就主管事務，對於各地方最高級行政長官之命令或處分認為有違背法令或逾越權限者，得提經行政院會議議決後停止或撤銷之。\n",
    "passed_date": "1949-04-19"
  },
  {
    "article": "4",
    "lyID": "01019",
    "content": "經濟部設左到各司：\n一、工業司。\n二、礦業司。\n三、商業司。\n四、總務司。\n",
    "passed_date": "1949-04-19"
  },
  {
    "article": "5",
    "lyID": "01019",
    "content": "經濟部設農林署，主管農林漁牧行政及業務，其組織另以法律定之。\n",
    "passed_date": "1949-04-19"
  },
  {
    "article": "6",
    "lyID": "01019",
    "content": "經濟部設水利署，主管水利行政及業務，其組織另以法律定之。\n",
    "passed_date": "1949-04-19"
  },
  {
    "article": "7",
    "lyID": "01019",
    "content": "經濟部設資源委員會主辦國營工礦電事業，其組織另以法律定之。\n",
    "passed_date": "1949-04-19"
  },
  {
    "article": "8",
    "lyID": "01019",
    "content": "經濟部為促進對外商務，得呈准行政院設駐外商務機構。\n",
    "passed_date": "1949-04-19"
  },
  {
    "article": "9",
    "lyID": "01019",
    "content": "工業司掌左列事項:\n一、關於全國工業之統籌配合事項。\n二、關於工業電業之獎進保護及監督事項。\n三、關於工業電廠之登記檢查及考核事項。\n四、關於工業團體業務之指導事項。\n五、關於工業技師之登記及監督事項。\n六、關於工業標準事項。\n七、關於工業專利特許事項。\n八、關於製造品及電氣器材之徵集試驗及檢定事項。\n九、關於國貨之獎勵及證明事項。\n十、關於其他工業行政事項。\n",
    "passed_date": "1949-04-19"
  },
  {
    "article": "10",
    "lyID": "01019",
    "content": "工業司掌左列事項:\n一、關於全國礦業之統籌配合事項。\n二、關於礦業之獎進保護及監督事項。\n三、關於礦權之設立與撤銷事項。\n四、關於礦業之登記檢查及考核事項。\n五、關於礦業技師之登記及監督事項。\n六、關於礦業用地礦業警察事項。\n七、關於地質調查事項。\n八、關於礦區稅之徵收事項。\n九、關於礦業爭議之處理事項。\n十、關於其他礦業行政事項。\n",
    "passed_date": "1949-04-19"
  },
  {
    "article": "11",
    "lyID": "01019",
    "content": "商業司掌左列事項:\n一、關於國內商業及國外貿易之獎進保護監督及推廣事項。\n二、關於輸出入之管理事項。\n三、關於商標之登記事項。\n四、關於交易所之登記監查及保險公司及特種營業之核准登記及監查事項。\n五、關於公司註冊及商號登記事項。\n六、關於商業團體業務之指導事項。\n七、關於會計師之登記及監督事項。\n八、關於商品檢驗及商品陳列展覽事項。\n九、關於商約商稅之研究事項。\n十、關於駐外商務官之指導監督事項。\n十一、關於其他商業行政事項。\n",
    "passed_date": "1949-04-19"
  },
  {
    "article": "12",
    "lyID": "01019",
    "content": "總務司掌左列事項：\n一、關於公文之收發分配撰擬及保管事項。\n二、關於部令之公布事項。\n三、關於印信之典守事項。\n四、關於本部公產公物之保管事項。\n五、關於款項之出納事項。\n六、關於本部出版物之編行事項。\n七、關於庶務事項。\n八、關於不屬於其他各司事項。\n",
    "passed_date": "1949-04-19"
  },
  {
    "article": "13",
    "lyID": "01019",
    "content": "經濟部部長特任，綜理本部事務，並指揮監督所屬職員及機關。\n",
    "passed_date": "1949-04-19"
  },
  {
    "article": "14",
    "lyID": "01019",
    "content": "經濟部政務次長常務次長，簡任，輔助部長處理部務。\n",
    "passed_date": "1949-04-19"
  },
  {
    "article": "15",
    "lyID": "01019",
    "content": "經濟部置參事四人至六人，簡任，撰擬審核關於本部法案命令。\n",
    "passed_date": "1949-04-19"
  },
  {
    "article": "16",
    "lyID": "01019",
    "content": "經濟部置秘書六人至八人，其中三人至五人簡任，餘薦任，分掌部務會議機要文件及長官交辦事務。\n",
    "passed_date": "1949-04-19"
  },
  {
    "article": "17",
    "lyID": "01019",
    "content": "經濟部置司長五人，簡任，分掌各司事務。\n",
    "passed_date": "1949-04-19"
  },
  {
    "article": "18",
    "lyID": "01019",
    "content": "經濟部置科長十八人至二十四人，薦任，科員六十人至一百人，委任，承長官之命，辦理各科事務。\n",
    "passed_date": "1949-04-19"
  },
  {
    "article": "19",
    "lyID": "01019",
    "content": "經濟部置技監二人，簡任，技正二十人至二十四人，其中八人至十二人簡任，餘薦任，技士三十四人至四十人，其中八人至十二人，薦任，餘委任。技佐二十六人至三十人，委任，承長官之命，辦理技術事務。\n",
    "passed_date": "1949-04-19"
  },
  {
    "article": "20",
    "lyID": "01019",
    "content": "經濟部為業務上之需要，得聘用專門人員十人至二十人。\n",
    "passed_date": "1949-04-19"
  },
  {
    "article": "21",
    "lyID": "01019",
    "content": "經濟部依事務上之需要，得酌用雇員。\n",
    "passed_date": "1949-04-19"
  },
  {
    "article": "22",
    "lyID": "01019",
    "content": "經濟部置會計長一人，統計長一人，均簡任，依法律之規定，辦理本部歲計會計及統計事項，會計處及統計處需用佐理人員名額，應就本法所定薦任委任人員及雇員名額內派充之。\n",
    "passed_date": "1949-04-19"
  },
  {
    "article": "23",
    "lyID": "01019",
    "content": "經濟部置人事室主任一人，薦任，依人事管理條例之規定，掌理本部人事事宜。\n人事室需用佐理人員名額，應就本法所定委任人員名額內派充之。\n",
    "passed_date": "1949-04-19"
  },
  {
    "article": "24",
    "lyID": "01019",
    "content": "經濟部處務規程以部令定之。\n",
    "passed_date": "1949-04-19"
  },
  {
    "article": "25",
    "lyID": "01019",
    "content": "本法自公布日施行。\n",
    "passed_date": "1949-04-19"
  },
  {
    "article": "24",
    "lyID": "01019",
    "content": "經濟部於必要時，得設各委員會，其組織以法律定之。\n",
    "passed_date": "1964-05-26"
  },
  {
    "article": "25",
    "lyID": "01019",
    "content": "經濟部處務規程，以部令定之。\n",
    "passed_date": "1964-05-26"
  },
  {
    "article": "26",
    "lyID": "01019",
    "content": "本法自公布日施行。\n",
    "passed_date": "1964-05-26"
  },
  {
    "article": "1",
    "lyID": "01019",
    "content": "經濟部主管全國經濟行政及經濟建設事務。\n",
    "passed_date": "1968-01-27",
    "title": "主管事務"
  },
  {
    "article": "2",
    "lyID": "01019",
    "content": "經濟部對於各地方最高級行政長官，執行本部主管事務，有指示、監督之責。\n",
    "passed_date": "1968-01-27",
    "title": "對主管事務之指示監督責任"
  },
  {
    "article": "3",
    "lyID": "01019",
    "content": "經濟部就主管事務，對於各地方最高級行政長官之命令或處分，認為有違背法令或逾越權限者，得提經行政院會議議決後，停止或撤銷之。\n",
    "passed_date": "1968-01-27",
    "title": "對違法、越權行為之處分"
  },
  {
    "article": "4",
    "lyID": "01019",
    "content": "經濟部設左列各司：\n一、農業司。\n二、礦業司。\n三、工業司。\n四、商業司。\n五、水利司。\n六、總務司。\n",
    "passed_date": "1968-01-27"
  },
  {
    "article": "5",
    "lyID": "01019",
    "content": "經濟部於必要時，得設各種委員會，其組織以法律定之。\n",
    "passed_date": "1968-01-27"
  },
  {
    "article": "6",
    "lyID": "01019",
    "content": "經濟部為促進對外經濟關係，得呈准行政院設置駐外經濟或商務機構。\n",
    "passed_date": "1968-01-27"
  },
  {
    "article": "7",
    "lyID": "01019",
    "content": "經濟部為開發重要資源，促進經濟建設，得呈准行政院創設或投資生產事業。\n前項生產事業為國營者，由經濟部設置機構管理之。\n",
    "passed_date": "1968-01-27"
  },
  {
    "article": "8",
    "lyID": "01019",
    "content": "農業司掌理左列事項：\n一、關於農林、漁牧政策及法規之擬訂事項。\n二、關於農林、漁牧事業之規劃、管理、輔導、監督及統籌配合事項。\n三、關於農林、漁牧情況之調查、研究事項。\n四、關於國際農業組織之聯繫事項。\n五、關於農林、漁牧事業之技術合作事項。\n六、關於農林、漁牧技術之改進、推廣及災害之防治事項。\n七、關於農林、漁牧使用藥品、肥料及機具之管理事項。\n八、關於農業技師之登記及監督事項。\n九、關於農林、漁牧團體目的事業之指導、監督事項。\n十、其他有關農林、漁牧行政事項。\n",
    "passed_date": "1968-01-27"
  },
  {
    "article": "9",
    "lyID": "01019",
    "content": "礦業司掌理左列事項：\n一、關於礦業政策及法規之擬訂事項。\n二、關於礦業之規劃、管理、輔導、監督及統籌配合事項。\n三、關於地質之調查及礦產資源之探勘、開發事項。\n四、關於礦業技術合作事項。\n五、關於礦業權之設定、變更、抵押及撤銷事項。\n六、關於礦業之登記、檢查、考核及爭議之處理事項。\n七、關於礦場安全之監督、指導事項。\n八、關於礦稅之核定及徵收事項。\n九、關於礦業技師之登記及監督事項。\n十、關於礦業團體目的事業之指導、監督事項。\n十一、其他有關礦業行政事項。\n",
    "passed_date": "1968-01-27"
  },
  {
    "article": "10",
    "lyID": "01019",
    "content": "工業司掌理左列事項：\n一、關於工業政策及法規之擬訂事項。\n二、關於工業之規劃、管理、輔導、監督及統籌配合事項。\n三、關於專利、國家標準及度量衡事項。\n四、關於工業技術合作及投資事項。\n五、關於工廠登記及考核事項。\n六、關於工業產品之試驗及檢定事項。\n七、關於工業技師之登記及監督事項。\n八、關於工業團體目的事業之指導、監督事項。\n九、其他有關工業行政事項。\n",
    "passed_date": "1968-01-27"
  },
  {
    "article": "11",
    "lyID": "01019",
    "content": "商業司掌理左列事項：\n一、關於商業及國際貿易政策、法規之擬訂事項。\n二、關於商業及國際貿易之規劃、管理、輔導、監督及統籌配合事項。\n三、關於商約、商稅之研究事項。\n四、關於商標註冊之監督事項。\n五、關於會計師、公司、特種營業之登記、管理及監督事項。\n六、關於物資調節及物價管理事項。\n七、關於商品檢驗之監督事項。\n八、關於商品之展覽、推廣事項。\n九、關於駐外經濟商務官之指導、監督事項。\n十、關於商業團體目的事業之指導、監督事項。\n十一、其他有關商業及國際貿易行政事項。\n",
    "passed_date": "1968-01-27"
  },
  {
    "article": "12",
    "lyID": "01019",
    "content": "水利司掌理左列事項：\n一、關於水利政策及法規之擬訂事項。\n二、關於水利建設之規劃、管理、興辦、輔導、監督及統籌配合事項。\n三、關於江、河、湖、泊之整治、疏濬、管理及養護事項。\n四、關於水道、水文之查勘、測記及水工、土工試驗、研究事項。\n五、關於國際水利組織之聯繫及水利技術合作事項。\n六、關於水權之登記、監督、處理事項。\n七、關於水利器材、物料之統籌調配事項。\n八、關於水利技術人員之登記、管理事項。\n九、關於水利團體之指導、監督事項。\n十、其他有關水利行政事項。\n",
    "passed_date": "1968-01-27"
  },
  {
    "article": "13",
    "lyID": "01019",
    "content": "總務司掌理左列事項：\n一、關於公文之收發、分配、繕校、撰擬及保管事項。\n二、關於部令之公布事項。\n三、關於印信之典守事項。\n四、關於本部公產、公物之保管事項。\n五、關於款項之出納、保管事項。\n六、關於本部出版物之印行事項。\n七、關於庶務事項。\n八、其他不屬於各司、處事項。\n",
    "passed_date": "1968-01-27"
  },
  {
    "article": "14",
    "lyID": "01019",
    "content": "經濟部部長，特任；綜理部務，指揮、監督所屬職員及機關。\n",
    "passed_date": "1968-01-27"
  },
  {
    "article": "15",
    "lyID": "01019",
    "content": "經濟部置政務次長一人，常務次長一人或二人，均簡任；輔助部長處理部務。\n",
    "passed_date": "1968-01-27"
  },
  {
    "article": "16",
    "lyID": "01019",
    "content": "經濟部置參事六人至八人，簡任；審核、研擬本部經濟政策、計畫方案、法律命令及部長交辦事項。\n",
    "passed_date": "1968-01-27"
  },
  {
    "article": "17",
    "lyID": "01019",
    "content": "經濟部置主任秘書一人，簡任；秘書六人至八人，其中三人至五人，簡任，餘薦任；掌理部務會議、機要文件，初核分辦、編輯公報、彙編施政計畫與施政報告及長官交辦事項。\n經濟部於必要時，得設秘書室。\n",
    "passed_date": "1968-01-27"
  },
  {
    "article": "18",
    "lyID": "01019",
    "content": "經濟部置司長六人，簡任；分掌各司事務；副司長六人，薦任或簡任；協助司長處理各司事務。\n",
    "passed_date": "1968-01-27"
  },
  {
    "article": "19",
    "lyID": "01019",
    "content": "經濟部置科長二十四人至二十六人，薦任；承長官之命，分掌各科事務；科員四十人至五十二人，委任，其中十人至二十人，得為薦任，辦事員九人至十五人，委任。\n",
    "passed_date": "1968-01-27"
  },
  {
    "article": "20",
    "lyID": "01019",
    "content": "經濟部置技監二人，簡任；技正二十人至二十五人，薦任，其中八人至十二人得為簡任；技士二十五人至三十人，委任，其中八人至十二人，得為薦任，辦理技術事務。\n",
    "passed_date": "1968-01-27"
  },
  {
    "article": "21",
    "lyID": "01019",
    "content": "經濟部置視察三人至五人，薦任，其中一人或二人，得為簡任；承長官之命，考察本部所屬機關之業務及調查交辦事項。\n",
    "passed_date": "1968-01-27"
  },
  {
    "article": "22",
    "lyID": "01019",
    "content": "經濟部置編審四人至六人，薦任或薦派；其中一人至三人，得為簡任或簡派。\n",
    "passed_date": "1968-01-27"
  },
  {
    "article": "23",
    "lyID": "01019",
    "content": "經濟部得聘任對經濟或其他科學有專門研究之人員三人至七人為顧問。\n",
    "passed_date": "1968-01-27"
  },
  {
    "article": "24",
    "lyID": "01019",
    "content": "經濟部置專門委員十二人至十六人，簡派；專員三人至五人，薦派。\n",
    "passed_date": "1968-01-27"
  },
  {
    "article": "25",
    "lyID": "01019",
    "content": "經濟部依事務上之需要，得酌用雇員，其名額以四十人為限。\n",
    "passed_date": "1968-01-27"
  },
  {
    "article": "26",
    "lyID": "01019",
    "content": "經濟部設人事處，置處長一人，簡任，依法掌理人事管理事項。\n人事處需用人員名額，應就本法規定人員名額內派充之。\n",
    "passed_date": "1968-01-27"
  },
  {
    "article": "27",
    "lyID": "01019",
    "content": "經濟部設會計處、置會計長一人，簡任；設統計處，置統計長一人，簡任，依法分掌歲計、會計及統計事項。\n會計處、統計處需用人員名額，應就本法規定人員名額內派充之。\n",
    "passed_date": "1968-01-27"
  },
  {
    "article": "28",
    "lyID": "01019",
    "content": "經濟部設研究發展委員會，由顧問、參事、專門人員及有關單位主管組成；所需工作人員，就法定員額內調充，其職掌如左：\n一、關於經濟政策及國內外經濟情況之分析研究事項。\n二、關於本部暨所屬機構業務之研究、發展事項。\n三、關於經濟動員準備措施之協調、聯繫、研究事項。\n四、關於經濟資料之蒐集及編譯、出版事業。\n五、其他有關經濟研究、發展事項。\n",
    "passed_date": "1968-01-27"
  },
  {
    "article": "29",
    "lyID": "01019",
    "content": "經濟部設法規委員會，由顧問、參事、專門人員及有關單位主管組成；所需工作人員，就法定員額內調充，其職掌如左：\n一、關於經濟法規之修訂、編纂及闡釋事項。\n二、關於有關法律案件之審議事項。\n三、關於業務行政涉及法律之審議事項。\n四、關於法律資料之蒐集、分析及研究事項。\n",
    "passed_date": "1968-01-27"
  },
  {
    "article": "30",
    "lyID": "01019",
    "content": "經濟部處務規程，由經濟部定之。\n",
    "passed_date": "1968-01-27"
  },
  {
    "article": "31",
    "lyID": "01019",
    "content": "本法自公布日施行。\n",
    "passed_date": "1968-01-27"
  },
  {
    "article": "4",
    "lyID": "01019",
    "content": "經濟部設左列各司、處、室：\n一、礦業司。\n二、商業司。\n三、水利司。\n四、總務司。\n五、國際合作處。\n六、投資業務處。\n七、技術處。\n八、秘書處。\n",
    "passed_date": "1981-01-06"
  },
  {
    "article": "5",
    "lyID": "01019",
    "content": "經濟部設農業局，掌理農、林、漁、牧、糧食政策、法規之擬訂及規劃、管理、統籌、協調與發展等事務；其組織以法律定之。\n",
    "passed_date": "1981-01-06"
  },
  {
    "article": "6",
    "lyID": "01019",
    "content": "經濟部設工業局，掌理工業政策、法規之擬訂及規劃、管理、統籌、協調與發展等事務；其組織以法律定之。\n",
    "passed_date": "1981-01-06",
    "title": "工業局之設置"
  },
  {
    "article": "7",
    "lyID": "01019",
    "content": "經濟部設國際貿易局，掌理國際貿易政策、法規之擬訂及規劃、管理、統籌、協調與發展等事務；其組織以法律定之。\n",
    "passed_date": "1981-01-06",
    "title": "國際貿易局之設置"
  },
  {
    "article": "8",
    "lyID": "01019",
    "content": "經濟部設中央標準局，其組織以法律定之。\n",
    "passed_date": "1981-01-06"
  },
  {
    "article": "9",
    "lyID": "01019",
    "content": "經濟部設商品檢驗局，其組織以法律定之。\n",
    "passed_date": "1981-01-06"
  },
  {
    "article": "10",
    "lyID": "01019",
    "content": "經濟部設能源委員會，其組織以法律定之。\n",
    "passed_date": "1981-01-06"
  },
  {
    "article": "11",
    "lyID": "01019",
    "content": "經濟部設水資源統一規劃委員會，其組織以法律定之。\n",
    "passed_date": "1981-01-06"
  },
  {
    "article": "12",
    "lyID": "01019",
    "content": "經濟部設中小企業處，其組織以法律定之。\n",
    "passed_date": "1981-01-06",
    "title": "中小企業處"
  },
  {
    "article": "13",
    "lyID": "01019",
    "content": "經濟部設加工出口區管理處，其組織以法律定之。\n",
    "passed_date": "1981-01-06",
    "title": "加工出口區管理處"
  },
  {
    "article": "14",
    "lyID": "01019",
    "content": "經濟部設中央地質調查所，其組織以法律定之。\n",
    "passed_date": "1981-01-06",
    "title": "中央地質調查所"
  },
  {
    "article": "15",
    "lyID": "01019",
    "content": "礦業司掌理左列事項：\n一、關於礦業政策及法規之擬訂事項。\n二、關於礦業之規劃、管理、輔導、監督及統籌配合事項。\n三、關於礦產資源之地質調查、探勘及開發之監督事項。\n四、關於國際礦業組織之聯繫及礦業技術合作事項。\n五、關於礦業權之設定、變更、抵押及撤銷事項。\n六、關於礦業之登記、檢查、考核及爭議之處理事項。\n七、關於礦場安全之監督、指導事項。\n八、關於礦稅之核定及徵收事項。\n九、關於礦業技師之登記及管理事項。\n十、關於礦業團體目的事業之指導、監督事項。\n十一、關於其他礦業行政事項。\n",
    "passed_date": "1981-01-06"
  },
  {
    "article": "16",
    "lyID": "01019",
    "content": "商業司掌理左列事項：\n一、關於商業政策及法規之擬訂事項。\n二、關於商業之規劃、管理、輔導、監督及統籌配合事項。\n三、關於商約、商稅之研究事項。\n四、關於商標註冊之監督事項。\n五、關於公司、商業之登記、管理及監督事項。\n六、關於物資調節及物價管理事項。\n七、關於商品檢驗之監督事項。\n八、關於商品之展覽、推廣事項。\n九、關於商業團體目的事業之指導、監督事項。\n十、關於其他商業行政事項。\n",
    "passed_date": "1981-01-06"
  },
  {
    "article": "17",
    "lyID": "01019",
    "content": "水利司掌理左列事項：\n一、關於水利政策及法規之擬訂事項。\n二、關於水利建設之規劃、管理、興辦、輔導、監督及統籌配合事項。\n三、關於江、河、湖、泊之整治、疏濬、管理及養護事項。\n四、關於水道、水文之查勘、測記及水工、土工試驗、研究事項。\n五、關於水庫安全與集水區治理、保護及有關協調事項。\n六、關於國際水利組織之聯繫及水利技術合作事項。\n七、關於水權之登記、監督、處理事項。\n八、關於水利技術人員之登記、管理事項。\n九、關於水利團體之指導、監督事項。\n十、關於其他水利行政事項。\n",
    "passed_date": "1981-01-06"
  },
  {
    "article": "18",
    "lyID": "01019",
    "content": "總務司掌理左列事項：\n一、關於文件之收發、分配、繕校及保管事項。\n二、關於部令之發布事項。\n三、關於印信之典守事項。\n四、關於公產、公物之保管事項。\n五、關於款項之出納事項。\n六、關於本部出版物之印行事項。\n七、關於庶務事項。\n八、關於不屬於其他各司、處、室事項。\n",
    "passed_date": "1981-01-06",
    "title": "總務司之職掌"
  },
  {
    "article": "19",
    "lyID": "01019",
    "content": "投資業務處掌理左列事項：\n一、關於國內外投資之促進事項。\n二、關於國內投資環境之研究及建議事項。\n三、關於投資機會之發掘及研究事項。\n四、關於投資計畫之推動、聯繫、協調及追蹤等事項。\n五、關於投資環境之報導及有關投資書刊之編撰事項。\n六、關於其他投資服務事項。\n",
    "passed_date": "1981-01-06"
  },
  {
    "article": "20",
    "lyID": "01019",
    "content": "國際合作處掌理左列事項：\n一、關於國際經濟及技術合作關係之聯繫、發展事項。\n二、關於國際經濟與技術合作活動之協調、推行事項。\n三、關於雙邊國家經濟合作之推動與經濟合作會議決議案執行之協調、聯繫及追蹤事項。\n四、關於區域性經濟與技術合作活動之聯繫、協調、推動及執行事項。\n五、關於對外技術協助之聯繫事項。\n六、關於雙邊國家技術協助計畫之執行事項。\n七、關於國際經濟與技術合作情況資料之蒐集、整理及研究事項。\n八、關於其他國際經濟及技術合作事項。\n",
    "passed_date": "1981-01-06",
    "title": "國際合作處之職掌"
  },
  {
    "article": "21",
    "lyID": "01019",
    "content": "技術處掌理左列事項：\n一、關於應用科學技術行政之聯繫、協調及督導事項。\n二、關於應用科學技術研究發展成果之推動、評估、追蹤事項。\n三、關於應用科學技術機構之聯繫及督導事項。\n四、關於國際科學技術情報之蒐集、分析、應用及指導事項。\n五、關於專利、標準、度量衡業務之聯繫及督導事項。\n六、關於其他應用科學之技術事項。\n",
    "passed_date": "1981-01-06",
    "title": "技術處之職掌"
  },
  {
    "article": "22",
    "lyID": "01019",
    "content": "秘書室掌理左列事項：\n一、關於機要公文、密電之處理及保管事項。\n二、關於文稿之撰擬、覆核、彙陳事項。\n三、關於部務會報之議事事項。\n四、關於年度施政方針、施政計畫、工作報告之彙編事項。\n五、關於施政之研究、發展及管制、考核事項。\n六、關於資料蒐集、研究、分析及報導事項。\n七、關於公共關係及新聞發布事項。\n八、部長、次長交辦事項。\n",
    "passed_date": "1981-01-06",
    "title": "秘書室之職掌"
  },
  {
    "article": "23",
    "lyID": "01019",
    "content": "經濟部部長，特任；綜理部務，指揮、監督所屬職員及機關。\n",
    "passed_date": "1981-01-06",
    "title": "經濟部部長"
  },
  {
    "article": "24",
    "lyID": "01019",
    "content": "經濟部置政務次長一人，職位比照第十四職等；常務次長二人，職位均列第十四職等，輔助部長處理部務。\n",
    "passed_date": "1981-01-06"
  },
  {
    "article": "25",
    "lyID": "01019",
    "content": "經濟部置主任秘書一人，參事八人至十人，技監二人至四人，司長四人，處長三人，專門委員四十一人至四十七人，職位均列第十至第十二職等；副司長四人，副處長三人，職位均列第九至第十一職等；秘書十三人至二十一人，視察四人至八人，技正二十四人至三十八人，編審十一人至十五人，職位均列第六至第九職等，其中秘書十人，視察四人，技正十九人，編審八人，得列第十或第十一職等；組長十四人至二十人，職位列第十或第十一職等；科長二十七人至三十三人，專員五十七人至七十三人，稽核二人至四人，職位均列第六至第九職等；技士二十五人至三十七人，職位列第三至第五職等，其中十三人得列第六或第七職等；組員二十四人至三十八人，科員四十九人至七十一人，職位均列第四或第五職等，其中組員十四人，科員二十四人得列第六或第七職等；辦事員四十五人至五十五人，職位列第三或第四職等；書記五十一人至六十九人，職位列第一至第三職等。\n",
    "passed_date": "1981-01-06"
  },
  {
    "article": "26",
    "lyID": "01019",
    "content": "經濟部設人事處，置處長一人；職位列第十至第十二職等；副處長一人，職位列第九至第十一職等；依法律規定，辦理人事管理事項。\n人事處所需工作人員應就本法所定員額內派充之。\n",
    "passed_date": "1981-01-06"
  },
  {
    "article": "27",
    "lyID": "01019",
    "content": "經濟部設會計處及統計處，置會計長及統計長各一人，職位均列等十至第十二職等；依法律規定分別辦理歲計、會計及統計事項。\n會計處及統計處所需工作人員，應就本法所定員額內派充之。\n",
    "passed_date": "1981-01-06"
  },
  {
    "article": "28",
    "lyID": "01019",
    "content": "第二十四條至第二十七條所定各職稱人員，其職位之職系依公務職位分類法及職系說明書就經建行政、工業行政、工業工程、商業行政、農業行政、田糧行政、林業行政、漁業行政、獸醫、礦業行政、地質、水利行政、水利工程、法制、圖書管理、民防、公共關係、出納、文書、一般行政管理、事務管理、會計、統計、人事行政、職位分類技術、打字及其他有關職系選用之。\n",
    "passed_date": "1981-01-06"
  },
  {
    "article": "29",
    "lyID": "01019",
    "content": "經濟部為應業務需要，得依聘用人員聘用條例之規定，聘用各種科技及經濟專門人員或對其他科學有專門研究之人員五十五人至九十九人。\n",
    "passed_date": "1981-01-06",
    "title": "聘用人員"
  },
  {
    "article": "30",
    "lyID": "01019",
    "content": "經濟部因業務需要，得報請行政院核准，另設各種委員會；所需工作人員，應就本法所定員額內調用之。\n",
    "passed_date": "1981-01-06",
    "title": "委員會"
  },
  {
    "article": "31",
    "lyID": "01019",
    "content": "經濟部為開發重要資源，促進經濟建設，得報請行政院核准創設或投資生產事業。\n前項生產事業為國營者，由經濟部設機構管理之。\n",
    "passed_date": "1981-01-06",
    "title": "生產事業"
  },
  {
    "article": "32",
    "lyID": "01019",
    "content": "經濟部為促進對外經濟關係，得報請行政院核准設駐外經濟或商務機構。\n",
    "passed_date": "1981-01-06",
    "title": "駐外經濟商務機構"
  },
  {
    "article": "33",
    "lyID": "01019",
    "content": "經濟部設研究發展委員會，由參事、專門人員及有關單位主管組成；所需工作人員，就法定員額內調充，掌理左列事項：\n一、關於經濟政策及國內外經濟情況之分析、研究事項。\n二、關於本部暨所屬機構業務之研究、發展事項。\n三、關於經濟動員準備措施之協調、聯繫、研究事項。\n四、關於經濟資料之蒐集及編譯、出版事項。\n五、關於其他經濟研究、發展事項。\n",
    "passed_date": "1981-01-06",
    "title": "研究發展委員會"
  },
  {
    "article": "34",
    "lyID": "01019",
    "content": "經濟部設法規委員會，由參事、專門人員及有關單位主管組成；所需工作人員，就法定員額內調充，掌理左列事項。\n一、關於經濟法規之修訂、編纂及解釋事項。\n二、關於有關法律案件之審議事項。\n三、關於業務行政涉及法律之審議事項。\n四、關於法律資料之蒐集、分析及研究事項。\n",
    "passed_date": "1981-01-06",
    "title": "法規委員會"
  },
  {
    "article": "35",
    "lyID": "01019",
    "content": "經濟部處務規程，由經濟部定之。\n",
    "passed_date": "1981-01-06",
    "title": "處務規程"
  },
  {
    "article": "36",
    "lyID": "01019",
    "content": "本法自公布日施行。\n",
    "passed_date": "1981-01-06"
  },
  {
    "article": "5",
    "lyID": "01019",
    "content": "（刪除）\n",
    "passed_date": "1984-07-13"
  },
  {
    "article": "27",
    "lyID": "01019",
    "content": "經濟部設會計處及統計處，置會計長及統計長各一人，職位均列第十至第十二職等；置副會計長及副統計長各一人，職位均列第十或第十一職等；依法律規定分別辦理歲計、會計及統計事項。\n會計處及統計處所需工作人員，應就本法所定員額內派充之。\n",
    "passed_date": "1984-07-13"
  },
  {
    "article": "28",
    "lyID": "01019",
    "content": "第二十四條至第二十七條所定各職稱人員，其職位之職系依公務職位分類法及職系說明書就經建行政、工業行政、工業工程、商業行政、礦業行政、地質、水利行政、水利工程、法制、圖書管理、民防、公共關係、出納、文書、一般行政管理、事務管理、會計、統計、人事行政、職位分類技術、打字及其他有關職系選用之。\n",
    "passed_date": "1984-07-13"
  },
  {
    "article": "4",
    "lyID": "01019",
    "content": "經濟部設下列各司、處、室：\n一、礦業司。\n二、商業司。\n三、總務司。\n四、國際合作處。\n五、投資業務處。\n六、技術處。\n七、秘書室。\n",
    "passed_date": "1996-09-19"
  },
  {
    "article": "8",
    "lyID": "01019",
    "content": "經濟部設智慧財產局；其組織以法律定之。\n",
    "passed_date": "1996-09-19",
    "title": "智慧財產局"
  },
  {
    "article": "9",
    "lyID": "01019",
    "content": "經濟部設標準檢驗局；其組織以法律定之。\n",
    "passed_date": "1996-09-19",
    "title": "標準檢驗局"
  },
  {
    "article": "11",
    "lyID": "01019",
    "content": "經濟部設水資源局；其組織以法律定之。\n",
    "passed_date": "1996-09-19"
  },
  {
    "article": "14-1",
    "lyID": "01019",
    "content": "經濟部設經貿人員訓練所；其組織以法律定之。\n",
    "passed_date": "1996-09-19",
    "title": "經貿人員訓練所"
  },
  {
    "article": "17",
    "lyID": "01019",
    "content": "（刪除）\n",
    "passed_date": "1996-09-19"
  },
  {
    "article": "24",
    "lyID": "01019",
    "content": "經濟部置政務次長一人，職務比照簡任第十四職等；常務次長二人，職務列簡任第十四職等，輔助部長處理部務。\n",
    "passed_date": "1996-09-19",
    "title": "政次、常次之設置"
  },
  {
    "article": "25",
    "lyID": "01019",
    "content": "經濟部置主任秘書一人，參事七人至九人，技監二人至四人，司長三人，處長三人，職務均列簡任第十二職等；副司長三人，副處長三人，職務均列簡任第十一職等；專門委員四十一人至四十七人，職務列簡任第十職等至第十一職等；秘書十三人至二十一人，視察四人至八人，技正十七人至三十一人，稽核二人至四人，職務均列薦任第八職等至第九職等，其中秘書十人，視察四人，技正十五人，得列簡任第十職等至第十一職等；科長四十人至五十二人，職務列薦任第九職等；專員七十人至八十六人，職務列薦任第七職等至第九職等；技士二十二人至三十四人，組員二十四人至三十八人，科員四十八人至七十人，職務均列委任第五職等，其中技士十一人，組員十四人，科員二十三人，得列薦任第六職等至第七職等；辦事員四十五人至五十五人，職務列委任第三職等至第四職等；書記五十一人至六十九人，職務列委任第一職等至第三職等。\n",
    "passed_date": "1996-09-19"
  },
  {
    "article": "26",
    "lyID": "01019",
    "content": "經濟部設人事處，置處長一人，職務列簡任第十二職等；副處長一人，職務列簡任第十一職等；依法辦理人事管理事項；所需工作人員，應就本法所定員額內派充之。\n",
    "passed_date": "1996-09-19",
    "title": "人事處之設置"
  },
  {
    "article": "27",
    "lyID": "01019",
    "content": "經濟部設會計處，置會計長一人，職務列簡任第十二職等；副會計長一人，職務列簡任第十一職等，依法辦理歲計、會計事項；所需工作人員，應就本法所定員額內派充之。\n",
    "passed_date": "1996-09-19",
    "title": "會計處之設置"
  },
  {
    "article": "27-1",
    "lyID": "01019",
    "content": "經濟部設統計處，置統計長一人，職務列簡任第十二職等；副統計長一人，職務列簡任第十一職等，依法辦理統計事項；所需工作人員，應就本法所定員額內派充之。\n",
    "passed_date": "1996-09-19",
    "title": "統計處之設置"
  },
  {
    "article": "27-2",
    "lyID": "01019",
    "content": "經濟部設政風處，置處長一人，職務列簡任第十二職等；依法辦理政風事項；所需工作人員，應就本法所定員額內派充之。\n",
    "passed_date": "1996-09-19",
    "title": "政風處之設置"
  },
  {
    "article": "28",
    "lyID": "01019",
    "content": "第二十四條至第二十七條之二所定列有官等職等人員，其職務所適用之職系，依公務人員任用法第八條之規定，就有關職系選用之。\n",
    "passed_date": "1996-09-19",
    "title": "職務適用職系"
  },
  {
    "article": "4",
    "lyID": "01019",
    "content": "經濟部設左列各處、司、室：\n一、國際合作處。\n二、技術處。\n三、總務司。\n四、秘書室。\n",
    "passed_date": "2002-01-04",
    "title": "司、處、室之設置"
  },
  {
    "article": "11",
    "lyID": "01019",
    "content": "經濟部設礦務局、商業局及水利署；其組織以法律定之。\n",
    "passed_date": "2002-01-04",
    "title": "礦務局、商業局及水利署"
  },
  {
    "article": "12-1",
    "lyID": "01019",
    "content": "經濟部設投資業務局；其組織以法律定之。\n",
    "passed_date": "2002-01-04",
    "title": "投資業務局"
  },
  {
    "article": "15",
    "lyID": "01019",
    "content": "（刪除）\n",
    "passed_date": "2002-01-04"
  },
  {
    "article": "16",
    "lyID": "01019",
    "content": "（刪除）\n",
    "passed_date": "2002-01-04"
  },
  {
    "article": "19",
    "lyID": "01019",
    "content": "（刪除）\n",
    "passed_date": "2002-01-04"
  },
  {
    "article": "25",
    "lyID": "01019",
    "content": "經濟部置主任秘書一人，參事九人至十二人，技監三人至六人，司長一人，處長二人，職務均列簡任第十二職等；副司長一人，副處長二人，職務均列簡任第十一職等；專門委員二十六人至三十二人，職務列簡任第十職等至第十一職等；秘書十二人至二十人，視察五人至九人，技正一人至十五人，稽核二人至四人，職務均列薦任第八職等至第九職等，其中秘書十人，視察四人，技正七人，職務得列簡任第十職等至第十一職等；科長三十六人至四十八人，職務列薦任第九職等；專員七十人至八十六人，職務列薦任第七職等至第九職等；技士三人至十五人，科員七十四人至一百十人，職務均列委任第五職等或薦任第六職等至第七職等；辦事員十四人至二十四人，職務列委任第三職等至第五職等；書記八人至二十六人，職務列委任第一職等至第三職等。\n",
    "passed_date": "2002-01-04",
    "title": "人員編制"
  },
  {
    "article": "36",
    "lyID": "01019",
    "content": "本法自公布日施行。\n本法修正條文施行日期，由行政院以命令定之。\n",
    "passed_date": "2002-01-04",
    "title": "施行日"
  },
  {
    "article": "10",
    "lyID": "01019",
    "content": "經濟部設能源局；其組織以法律定之。\n",
    "passed_date": "2004-01-09",
    "title": "能源局"
  }
]